README.md
api.py
constants.py
dbtools.py
exceptions.py
legacy.py
misc.py
prints.py
schemes.py
setup.py
utils.py
blockhubdpostools.egg-info/PKG-INFO
blockhubdpostools.egg-info/SOURCES.txt
blockhubdpostools.egg-info/dependency_links.txt
blockhubdpostools.egg-info/top_level.txt