Metadata-Version: 1.0
Name: blockhubdpostools
Version: 0.0.1
Summary: General tools for interacting with DPOS chains
Home-page: https://github.com/BlockHub/blockhubdpostools
Author: karel
Author-email: karel@blockhub.nl
License: MIT
Platform: UNKNOWN
